nonebot_plugin_ACMD/__init__.py
nonebot_plugin_ACMD/ACMD_driver.py
nonebot_plugin_ACMD/already_handler.py
nonebot_plugin_ACMD/Atypes.py
nonebot_plugin_ACMD/command.py
nonebot_plugin_ACMD/command_signer.py
nonebot_plugin_ACMD/config.py
nonebot_plugin_ACMD/connection_pool.py
nonebot_plugin_acmd-0.0.6.dist-info/LICENSE
nonebot_plugin_acmd-0.0.6.dist-info/METADATA
nonebot_plugin_acmd-0.0.6.dist-info/WHEEL
nonebot_plugin_acmd-0.0.6.dist-info/RECORD
