Metadata-Version: 2.3
Name: nonebot_plugin_ACMD
Version: 0.0.6
Summary: 一个专注于解决输入问题的命令实现。
License: AGPL-3.0
Author: hlfzsi
Requires-Python: >=3.10,<4.0
Classifier: License :: OSI Approved :: GNU Affero General Public License v3
Classifier: Programming Language :: Python :: 3
Classifier: Programming Language :: Python :: 3.10
Classifier: Programming Language :: Python :: 3.11
Classifier: Programming Language :: Python :: 3.12
Classifier: Programming Language :: Python :: 3.13
Requires-Dist: aiofiles (>=24.1.0,<25.0.0)
Requires-Dist: aiosqlite (>=0.20.0,<0.21.0)
Requires-Dist: httpx (>=0.28.1,<0.29.0)
Requires-Dist: nonebot-adapter-onebot (>=2.4.6,<3.0.0)
Requires-Dist: nonebot2 (>=2.4.1,<3.0.0)
Requires-Dist: pypinyin (>=0.53.0,<0.54.0)
Requires-Dist: rapidfuzz (>=3.11.0,<4.0.0)
